{
    "hospitals": [
        {
            "name": "Ho\u00e0n M\u1ef9",
            "address": "C\u00e1i R\u0103ng, C\u1ea7n Th\u01a1",
            "phone": "(+84) 874310054"
        },
        {
            "name": "\u0110a Khoa Trung \u01af\u01a1ng C\u1ea7n Th\u01a1",
            "address": "C\u00e1i R\u0103ng, C\u1ea7n Th\u01a1",
            "phone": "(+84) 989770463"
        },
        {
            "name": "121",
            "address": "Ninh Ki\u1ec1u, C\u1ea7n Th\u01a1",
            "phone": "(+84) 561010087"
        },
        {
            "name": "Ch\u1ee3 R\u1eaby",
            "address": "TP. H\u1ed3 Ch\u00ed Minh",
            "phone": "(+84) 551111125"
        }
    ],
    "users": [
        {
            "email": "admin@gmail.com",
            "password": "admin",
            "isAdmin": true
        },
        {
            "email": "hoanmy@judoh.io",
            "isAdmin": false
        },
        {
            "email": "dakhoatrunguongcantho@judoh.io",
            "isAdmin": false
        },
        {
            "email": "121@judoh.io",
            "isAdmin": false
        },
        {
            "email": "choray@judoh.io",
            "isAdmin": false
        }
    ],
    "events": [
        {
            "name": "Health and Wellbeing at work",
            "location": {
                "address": "Khoa CNTT, \u0110\u1ea1i H\u1ecdc C\u1ea7n Th\u01a1",
                "city": "C\u1ea7n Th\u01a1"
            },
            "startDate": "1641315600000",
            "duration": 3,
            "detail": "The aim is to raise global awareness of the need for safe blood and blood products for transfusion and of the critical contribution voluntary, unpaid blood donors make to national health systems.",
            "dateCreated": "1639267200000"
        },
        {
            "name": "Judoh Blood Donations",
            "location": {
                "address": "s\u1ed1 20, t\u00f2a nh\u00e0 ALianz, Qu\u1eadn 7",
                "city": "TP. H\u1ed3 Ch\u00ed Minh"
            },
            "startDate": "1647277200000",
            "duration": 2,
            "detail": "Safe blood and blood products and their transfusion are a critical aspect of care and public health. They save millions of lives and improve the health and quality of life of many patients every day.",
            "dateCreated": "1644451200000"
        },
        {
            "name": "We are Donors",
            "location": {
                "address": "L\u00e0ng B\u01b0\u1edfi, \u00d4 M\u00f4n",
                "city": "C\u1ea7n Th\u01a1"
            },
            "startDate": "1648746000000",
            "duration": 1,
            "detail": "Throughout the COVID-19 pandemic, despite limited mobility and other challenges, blood donors in many countries have continued to donate blood and plasma to patients who need transfusion. ",
            "dateCreated": "1646092800000"
        },
        {
            "name": "Judoh Blood Donations - Summer Edition",
            "location": {
                "address": "SVD Th\u1ed1ng Nh\u1ea5t",
                "city": "TP. H\u1ed3 Ch\u00ed Minh"
            },
            "startDate": "1649264400000",
            "duration": 100,
            "detail": "Encourage youth to embrace the humanitarian call to donate blood and inspire others to do the same",
            "dateCreated": "1646611200000"
        },
        {
            "name": "Judoh Blood Donations - Christmast Edition",
            "location": {
                "address": "SVD H\u00e0ng \u0110\u1eaby",
                "city": "H\u00e0 N\u1ed9i"
            },
            "startDate": "1671642000000",
            "duration": 2,
            "detail": "Encourage youth to embrace the humanitarian call to donate blood and inspire others to do the same",
            "dateCreated": "1651363200000"
        }
    ],
    "donors": [
        {
            "__eventName": "Health and Wellbeing at work",
            "listParticipants": [
                {
                    "_id": "015170423564",
                    "name": "Tr\u1ea7n Thanh Phong",
                    "dob": "620413200000",
                    "gender": "male",
                    "address": "Ngã 6, Hậu Giang",
                    "phone": "(+84) 754499576",
                    "email": "ttp30081989@gmail.com",
                    "transaction": {
                        "blood": {
                            "name": "O",
                            "type": "Positive"
                        },
                        "dateDonated": 1641402000000,
                        "amount": 108,
                        "status": 1
                    }
                },
                {
                    "_id": "331952647287",
                    "name": "Ng\u00f4 C\u1ea3nh Tu\u1ea5n",
                    "dob": "156528000000",
                    "gender": "male",
                    "address": "Ô Môn, Cần Thơ",
                    "phone": "(+84) 032124499",
                    "email": "nct18121974@gmail.com",
                    "transaction": {
                        "blood": {
                            "name": "B",
                            "type": "Positive"
                        },
                        "dateDonated": 1641315600000,
                        "amount": 129,
                        "status": 1
                    }
                },
                {
                    "_id": "406682808563",
                    "name": "Nguy\u1ec5n Vi\u1ec7t Tuy\u1ebft",
                    "dob": "587322000000",
                    "gender": "female",
                    "address": "Bình Thủy, Cần Thơ",
                    "phone": "(+84) 035300191",
                    "email": "nvt12081988@gmail.com",
                    "transaction": {
                        "blood": {
                            "name": "AB",
                            "type": "Positive"
                        },
                        "dateDonated": 1641402000000,
                        "amount": 135,
                        "status": 1
                    }
                },
                {
                    "_id": "438174401806",
                    "name": "Tr\u1ea7n B\u0103ng T\u00e2m",
                    "dob": "794682000000",
                    "gender": "female",
                    "address": "Cờ Đỏ, Cần Thơ",
                    "phone": "(+84) 790066227",
                    "email": "tbt09031995@gmail.com",
                    "transaction": {
                        "blood": {
                            "name": "B",
                            "type": "Positive"
                        },
                        "dateDonated": 1641488400000,
                        "amount": 129,
                        "status": 1
                    }
                },
                {
                    "_id": "844192507377",
                    "name": "B\u00f9i Th\u00e1i H\u00f2a",
                    "dob": "355597200000",
                    "gender": "male",
                    "address": "Bình Minh, Vĩnh Long",
                    "phone": "(+84) 743292618",
                    "email": "bth09041981@gmail.com",
                    "transaction": {
                        "blood": {
                            "name": "AB",
                            "type": "Negative"
                        },
                        "dateDonated": 1641315600000,
                        "amount": 110,
                        "status": 1
                    }
                },
                {
                    "_id": "054317564294",
                    "name": "Ng\u00f4 Ph\u00fac Sinh",
                    "dob": "990291600000",
                    "gender": "male",
                    "address": "Thốt Nốt, Cần Thơ",
                    "phone": "(+84) 696197954",
                    "email": "nps20052001@gmail.com",
                    "transaction": {
                        "blood": {
                            "name": "O",
                            "type": "Negative"
                        },
                        "dateDonated": 1641315600000,
                        "amount": 100,
                        "status": 1
                    }
                },
                {
                    "_id": "678374151115",
                    "name": "Ng\u00f4 Xu\u00e2n Tr\u01b0\u1eddng",
                    "dob": "67968000000",
                    "gender": "male",
                    "address": "Ô Môn, Cần Thơ",
                    "phone": "(+84) 779250774",
                    "email": "nxt27021972@gmail.com",
                    "transaction": {
                        "blood": {
                            "name": "O",
                            "type": "Negative"
                        },
                        "dateDonated": 1641402000000,
                        "amount": 114,
                        "status": 1
                    }
                },
                {
                    "_id": "825465082815",
                    "name": "Nguy\u1ec5n Kh\u1ea3i Tu\u1ea5n",
                    "dob": "945363600000",
                    "gender": "male",
                    "address": "Giồng Riềng, Kiên Giang",
                    "phone": "(+84) 548052468",
                    "email": "nkt17121999@gmail.com",
                    "transaction": {
                        "blood": {
                            "name": "A",
                            "type": "Negative"
                        },
                        "dateDonated": 1641488400000,
                        "amount": 140,
                        "status": 1
                    }
                },
                {
                    "_id": "823061923803",
                    "name": "Tr\u01b0\u01a1ng \u00c1nh Hoa",
                    "dob": "862938000000",
                    "gender": "female",
                    "address": "Tri Tôn, An Giang",
                    "phone": "(+84) 697991925",
                    "email": "tah07051997@gmail.com",
                    "transaction": {
                        "blood": {
                            "name": "AB",
                            "type": "Negative"
                        },
                        "dateDonated": 1641402000000,
                        "amount": 129,
                        "status": 1
                    }
                },
                {
                    "_id": "848913663028",
                    "name": "L\u00ea Thi\u1ec7u B\u1ea3o",
                    "dob": "43084800000",
                    "gender": "male",
                    "address": "Mộc Hóa, Long An",
                    "phone": "(+84) 624293629",
                    "email": "ltb15051971@gmail.com",
                    "transaction": {
                        "blood": {
                            "name": "B",
                            "type": "Positive"
                        },
                        "dateDonated": 1641402000000,
                        "amount": 112,
                        "status": -1,
                        "rejectReason": "Hepatitis B and C"
                    }
                },
                {
                    "_id": "380410686864",
                    "name": "Tr\u1ea7n Kim Thy",
                    "dob": "476816400000",
                    "gender": "female",
                    "address": "Quận 1, TP HCM",
                    "phone": "(+84) 596580266",
                    "email": "tkt10021985@gmail.com",
                    "transaction": {
                        "blood": {
                            "name": "A",
                            "type": "Positive"
                        },
                        "dateDonated": 1641402000000,
                        "amount": 146,
                        "status": -1,
                        "rejectReason": "Hepatitis B and C"
                    }
                },
                {
                    "_id": "928042123245",
                    "name": "B\u00f9i Khu\u00ea Trung",
                    "dob": "777229200000",
                    "gender": "female",
                    "address": "Quận 10, TP HCM",
                    "phone": "(+84) 052154190",
                    "email": "bkt19081994@gmail.com",
                    "transaction": {
                        "blood": {
                            "name": "O",
                            "type": "Negative"
                        },
                        "dateDonated": 1641402000000,
                        "amount": 112,
                        "status": -1,
                        "rejectReason": "Chronic alcoholism"
                    }
                }
            ]
        },
        {
            "__eventName": "Judoh Blood Donations",
            "listParticipants": [
                {
                    "_id": "625164290733",
                    "name": "Tr\u1ea7n Th\u00e0nh Sang",
                    "dob": "216752400000",
                    "gender": "male",
                    "address": "Quận 12, TP HCM",
                    "phone": "(+84) 426121395",
                    "email": "tts14111976@gmail.com",
                    "transaction": {
                        "blood": {
                            "name": "O",
                            "type": "Negative"
                        },
                        "dateDonated": 1647363600000,
                        "amount": 120,
                        "status": 1
                    }
                },
                {
                    "_id": "484714949896",
                    "name": "Ng\u00f4 \u00d0\u00f4ng Tuy\u1ec1n",
                    "dob": "711046800000",
                    "gender": "female",
                    "address": "Cái Răng, Cần Thơ",
                    "phone": "(+84) 225042020",
                    "email": "ndt14071992@gmail.com",
                    "transaction": {
                        "blood": {
                            "name": "O",
                            "type": "Positive"
                        },
                        "dateDonated": 1647277200000,
                        "amount": 125,
                        "status": 1
                    }
                },
                {
                    "_id": "437249400607",
                    "name": "L\u00ea Cam Th\u1ea3o",
                    "dob": "731178000000",
                    "gender": "female",
                    "address": "Phú Nhuận, TP HCM",
                    "phone": "(+84) 773828964",
                    "email": "lct04031993@gmail.com",
                    "transaction": {
                        "blood": {
                            "name": "A",
                            "type": "Negative"
                        },
                        "dateDonated": 1647277200000,
                        "amount": 132,
                        "status": 1
                    }
                },
                {
                    "_id": "132550587370",
                    "name": "Tr\u01b0\u01a1ng \u00d0\u1ea1i Ng\u1ecdc",
                    "dob": "151689600000",
                    "gender": "male",
                    "address": "Tân Bình, TP HCM",
                    "phone": "(+84) 869226528",
                    "email": "tdn23101974@gmail.com",
                    "transaction": {
                        "blood": {
                            "name": "B",
                            "type": "Positive"
                        },
                        "dateDonated": 1647363600000,
                        "amount": 140,
                        "status": 1
                    }
                },
                {
                    "_id": "537653285431",
                    "name": "Nguy\u1ec5n Xu\u00e2n Nhi\u00ean",
                    "dob": "62870400000",
                    "gender": "female",
                    "address": "Cai Lậy, Tiền Giang",
                    "phone": "(+84) 344475377",
                    "email": "nxn30121971@gmail.com",
                    "transaction": {
                        "blood": {
                            "name": "AB",
                            "type": "Positive"
                        },
                        "dateDonated": 1647363600000,
                        "amount": 101,
                        "status": 1
                    }
                },
                {
                    "_id": "623496365465",
                    "name": "Tr\u01b0\u01a1ng Linh Nhi",
                    "dob": "516128400000",
                    "gender": "female",
                    "address": "Quận 3, TP HCM",
                    "phone": "(+84) 607311135",
                    "email": "tln11051986@gmail.com",
                    "transaction": {
                        "blood": {
                            "name": "B",
                            "type": "Positive"
                        },
                        "dateDonated": 1647363600000,
                        "amount": 127,
                        "status": 1
                    }
                },
                {
                    "_id": "239597492430",
                    "name": "B\u00f9i C\u00f4ng L\u1ed9c",
                    "dob": "879958800000",
                    "gender": "male",
                    "address": "Ba Tri, Bến Tre",
                    "phone": "(+84) 134306466",
                    "email": "bcl20111997@gmail.com",
                    "transaction": {
                        "blood": {
                            "name": "AB",
                            "type": "Negative"
                        },
                        "dateDonated": 1647277200000,
                        "amount": 123,
                        "status": 1
                    }
                },
                {
                    "_id": "205304597404",
                    "name": "Ng\u00f4 D\u01b0\u01a1ng Kh\u00e1nh",
                    "dob": "1065632400000",
                    "gender": "male",
                    "address": "Bảo Lộc, Lâm Đồng",
                    "phone": "(+84) 706015055",
                    "email": "ndk09102003@gmail.com",
                    "transaction": {
                        "blood": {
                            "name": "A",
                            "type": "Positive"
                        },
                        "dateDonated": 1647363600000,
                        "amount": 148,
                        "status": 1
                    }
                },
                {
                    "_id": "332451414278",
                    "name": "L\u00ea Vi\u1ec7t Kh\u1ea3i",
                    "dob": "913136400000",
                    "gender": "male",
                    "address": "Bến Lức, Long An",
                    "phone": "(+84) 763582821",
                    "email": "lvk09121998@gmail.com",
                    "transaction": {
                        "blood": {
                            "name": "O",
                            "type": "Positive"
                        },
                        "dateDonated": 1647277200000,
                        "amount": 125,
                        "status": 1
                    }
                },
                {
                    "_id": "428458938363",
                    "name": "Tr\u1ea7n Gia Ki\u00ean",
                    "dob": "205002000000",
                    "gender": "male",
                    "address": "Bình Chánh, TP HCM",
                    "phone": "(+84) 946994503",
                    "email": "tgk01071976@gmail.com",
                    "transaction": {
                        "blood": {
                            "name": "AB",
                            "type": "Negative"
                        },
                        "dateDonated": 1647363600000,
                        "amount": 126,
                        "status": 1
                    }
                },
                {
                    "_id": "532468928496",
                    "name": "Nguy\u1ec5n Tr\u00e0 My",
                    "dob": "1053104400000",
                    "gender": "female",
                    "address": "Cái Bè, Tiền Giang",
                    "phone": "(+84) 852510819",
                    "email": "ntm17052003@gmail.com",
                    "transaction": {
                        "blood": {
                            "name": "O",
                            "type": "Negative"
                        },
                        "dateDonated": 1647363600000,
                        "amount": 109,
                        "status": -1,
                        "rejectReason": "Cancer"
                    }
                },
                {
                    "_id": "343662199463",
                    "name": "Nguy\u1ec5n H\u1ea1 Giang",
                    "dob": "16214400000",
                    "gender": "female",
                    "address": "Cần Đước, Long An",
                    "phone": "(+84) 178580451",
                    "email": "nhg08071970@gmail.com",
                    "transaction": {
                        "blood": {
                            "name": "A",
                            "type": "Negative"
                        },
                        "dateDonated": 1647277200000,
                        "amount": 101,
                        "status": -1,
                        "rejectReason": "Cardiac disease"
                    }
                },
                {
                    "_id": "793571092028",
                    "name": "L\u00ea Th\u00f4ng Minh",
                    "dob": "761850000000",
                    "gender": "male",
                    "address": "Cao Lãnh, Đồng Tháp",
                    "phone": "(+84) 014712535",
                    "email": "ltm22021994@gmail.com",
                    "transaction": {
                        "blood": {
                            "name": "B",
                            "type": "Negative"
                        },
                        "dateDonated": 1647277200000,
                        "amount": 125,
                        "status": -1,
                        "rejectReason": "High risk occupation"
                    }
                }
            ]
        },
        {
            "__eventName": "We are Donors",
            "listParticipants": [
                {
                    "_id": "343275880278",
                    "name": "Tr\u1ea7n \u0110\u0103ng Quang",
                    "dob": "806432400000",
                    "gender": "male",
                    "address": "Châu Đốc, An Giang",
                    "phone": "(+84) 419413160",
                    "email": "tdq23071995@gmail.com",
                    "transaction": {
                        "blood": {
                            "name": "B",
                            "type": "Negative"
                        },
                        "dateDonated": 1648746000000,
                        "amount": 116,
                        "status": 1
                    }
                },
                {
                    "_id": "568516233703",
                    "name": "L\u00ea Th\u1ee5y Du",
                    "dob": "264618000000",
                    "gender": "female",
                    "address": "Châu Thành, Đồng Tháp",
                    "phone": "(+84) 381314524",
                    "email": "ltd22051978@gmail.com",
                    "transaction": {
                        "blood": {
                            "name": "AB",
                            "type": "Negative"
                        },
                        "dateDonated": 1648746000000,
                        "amount": 149,
                        "status": 1
                    }
                },
                {
                    "_id": "504321249636",
                    "name": "Tr\u1ea7n H\u00f9ng T\u01b0\u1eddng",
                    "dob": "1033837200000",
                    "gender": "male",
                    "address": "Chợ Gạo, Tiền Giang",
                    "phone": "(+84) 778268910",
                    "email": "tht06102002@gmail.com",
                    "transaction": {
                        "blood": {
                            "name": "A",
                            "type": "Positive"
                        },
                        "dateDonated": 1648746000000,
                        "amount": 105,
                        "status": 1
                    }
                },
                {
                    "_id": "273488618725",
                    "name": "Tr\u01b0\u01a1ng \u0110\u00f4ng Tuy\u1ec1n",
                    "dob": "479408400000",
                    "gender": "female",
                    "address": "Thốt Nốt, Cần Thơ",
                    "phone": "(+84) 397355135",
                    "email": "tdt12031985@gmail.com",
                    "transaction": {
                        "blood": {
                            "name": "O",
                            "type": "Positive"
                        },
                        "dateDonated": 1648746000000,
                        "amount": 132,
                        "status": 1
                    }
                },
                {
                    "_id": "152173137065",
                    "name": "Tr\u01b0\u01a1ng Tu\u1ea5n \u00d0\u1ee9c",
                    "dob": "615834000000",
                    "gender": "male",
                    "address": "Thốt Nốt, Cần Thơ",
                    "phone": "(+84) 060114266",
                    "email": "ttd08071989@gmail.com",
                    "transaction": {
                        "blood": {
                            "name": "O",
                            "type": "Positive"
                        },
                        "dateDonated": 1648746000000,
                        "amount": 143,
                        "status": 1
                    }
                },
                {
                    "_id": "105346519430",
                    "name": "Ng\u00f4 Cao Nghi\u1ec7p",
                    "dob": "596394000000",
                    "gender": "male",
                    "address": "Dĩ An, Bình Dương",
                    "phone": "(+84) 168470233",
                    "email": "ncn25111988@gmail.com",
                    "transaction": {
                        "blood": {
                            "name": "A",
                            "type": "Negative"
                        },
                        "dateDonated": 1648746000000,
                        "amount": 136,
                        "status": 1
                    }
                },
                {
                    "_id": "426527880300",
                    "name": "Ng\u00f4 H\u1ed3ng Nh\u1ea1n",
                    "dob": "863542800000",
                    "gender": "female",
                    "address": "Duyên Hải, Trà Vinh",
                    "phone": "(+84) 663788580",
                    "email": "nhn14051997@gmail.com",
                    "transaction": {
                        "blood": {
                            "name": "O",
                            "type": "Negative"
                        },
                        "dateDonated": 1648746000000,
                        "amount": 122,
                        "status": 1
                    }
                },
                {
                    "_id": "788289929724",
                    "name": "L\u00ea Y\u00ean \u00d0an",
                    "dob": "268419600000",
                    "gender": "female",
                    "address": "Giồng Riềng, Kiên Giang",
                    "phone": "(+84) 540727040",
                    "email": "lyd05071978@gmail.com",
                    "transaction": {
                        "blood": {
                            "name": "B",
                            "type": "Negative"
                        },
                        "dateDonated": 1648746000000,
                        "amount": 137,
                        "status": 1
                    }
                },
                {
                    "_id": "910743850316",
                    "name": "L\u00ea Thanh Giang",
                    "dob": "824835600000",
                    "gender": "female",
                    "address": "Gò Quao, Kiên Giang",
                    "phone": "(+84) 587834612",
                    "email": "ltg21021996@gmail.com",
                    "transaction": {
                        "blood": {
                            "name": "A",
                            "type": "Positive"
                        },
                        "dateDonated": 1648746000000,
                        "amount": 119,
                        "status": 1
                    }
                },
                {
                    "_id": "913542751853",
                    "name": "B\u00f9i Vi\u1ec5n Ph\u01b0\u01a1ng",
                    "dob": "551898000000",
                    "gender": "male",
                    "address": "Gò Công, Tiền Giang",
                    "phone": "(+84) 259678084",
                    "email": "bvp29061987@gmail.com",
                    "transaction": {
                        "blood": {
                            "name": "A",
                            "type": "Positive"
                        },
                        "dateDonated": 1648746000000,
                        "amount": 126,
                        "status": 1
                    }
                },
                {
                    "_id": "475884592851",
                    "name": "Nguy\u1ec5n Anh V\u0169",
                    "dob": "1022864400000",
                    "gender": "male",
                    "address": "Hà Tiên, Kiên Giang",
                    "phone": "(+84) 586270093",
                    "email": "nav01062002@gmail.com",
                    "transaction": {
                        "blood": {
                            "name": "AB",
                            "type": "Negative"
                        },
                        "dateDonated": 1648746000000,
                        "amount": 132,
                        "status": -1,
                        "rejectReason": "Cardiac disease"
                    }
                },
                {
                    "_id": "943382494824",
                    "name": "Tr\u1ea7n B\u00edch Hi\u1ec1n",
                    "dob": "966445200000",
                    "gender": "female",
                    "address": "Hòa Bình, Bạc Liêu",
                    "phone": "(+84) 682372934",
                    "email": "tbh17082000@gmail.com",
                    "transaction": {
                        "blood": {
                            "name": "A",
                            "type": "Positive"
                        },
                        "dateDonated": 1648746000000,
                        "amount": 130,
                        "status": -1,
                        "rejectReason": "Sever lung disease"
                    }
                }
            ]
        },
        {
            "__eventName": "Judoh Blood Donations - Summer Edition",
            "listParticipants": [
                {
                    "_id": "569920221547",
                    "name": "Ng\u00f4 T\u00e0i Nguy\u00ean",
                    "dob": "950115600000",
                    "gender": "male",
                    "address": "Hà Tiên, Kiên Giang",
                    "phone": "(+84) 588485660",
                    "email": "ntn10022000@gmail.com",
                    "transaction": {
                        "blood": {
                            "name": "A",
                            "type": "Negative"
                        },
                        "dateDonated": 1653930000000,
                        "amount": 119,
                        "status": 1
                    }
                },
                {
                    "_id": "116866330350",
                    "name": "Tr\u1ea7n Qu\u1ebf Linh",
                    "dob": "842720400000",
                    "gender": "female",
                    "address": "Hồng Ngự, Đồng Tháp",
                    "phone": "(+84) 351809016",
                    "email": "tql15091996@gmail.com",
                    "transaction": {
                        "blood": {
                            "name": "B",
                            "type": "Positive"
                        },
                        "dateDonated": 1654621200000,
                        "amount": 112,
                        "status": 1
                    }
                },
                {
                    "_id": "171921185689",
                    "name": "Nguy\u1ec5n Ch\u00ed C\u00f4ng",
                    "dob": "787770000000",
                    "gender": "male",
                    "address": "Kế Sách, Sóc Trăng",
                    "phone": "(+84) 642371646",
                    "email": "ncc19121994@gmail.com",
                    "transaction": {
                        "blood": {
                            "name": "A",
                            "type": "Positive"
                        },
                        "dateDonated": 1650214800000,
                        "amount": 100,
                        "status": 1
                    }
                },
                {
                    "_id": "070270856900",
                    "name": "Nguy\u1ec5n \u00d0an Thu",
                    "dob": "960742800000",
                    "gender": "female",
                    "address": "Lai Vung, Đồng Tháp",
                    "phone": "(+84) 582832042",
                    "email": "ndt12062000@gmail.com",
                    "transaction": {
                        "blood": {
                            "name": "O",
                            "type": "Positive"
                        },
                        "dateDonated": 1654362000000,
                        "amount": 121,
                        "status": 1
                    }
                },
                {
                    "_id": "819241095127",
                    "name": "Tr\u1ea7n H\u1ea3i Ph\u01b0\u01a1ng",
                    "dob": "490467600000",
                    "gender": "female",
                    "address": "Kế Sách, Sóc Trăng",
                    "phone": "(+84) 802607279",
                    "email": "thp18071985@gmail.com",
                    "transaction": {
                        "blood": {
                            "name": "A",
                            "type": "Negative"
                        },
                        "dateDonated": 1649523600000,
                        "amount": 146,
                        "status": 1
                    }
                },
                {
                    "_id": "686346069843",
                    "name": "Tr\u01b0\u01a1ng Ch\u00ed B\u1ea3o",
                    "dob": "1007571600000",
                    "gender": "male",
                    "address": "Long Mỹ, Hậu Giang",
                    "phone": "(+84) 507083295",
                    "email": "tcb06122001@gmail.com",
                    "transaction": {
                        "blood": {
                            "name": "AB",
                            "type": "Positive"
                        },
                        "dateDonated": 1657040400000,
                        "amount": 107,
                        "status": 1
                    }
                },
                {
                    "_id": "691236858604",
                    "name": "Tr\u01b0\u01a1ng H\u1ea3i Th\u1ee5y",
                    "dob": "954435600000",
                    "gender": "female",
                    "address": "Long Xuyên, An Giang",
                    "phone": "(+84) 554283102",
                    "email": "tht31032000@gmail.com",
                    "transaction": {
                        "blood": {
                            "name": "O",
                            "type": "Positive"
                        },
                        "dateDonated": 1653670800000,
                        "amount": 141,
                        "status": 1
                    }
                },
                {
                    "_id": "522577599435",
                    "name": "Tr\u1ea7n Quang Danh",
                    "dob": "984243600000",
                    "gender": "male",
                    "address": "Mang Thít, Vĩnh Long",
                    "phone": "(+84) 152299047",
                    "email": "tqd11032001@gmail.com",
                    "transaction": {
                        "blood": {
                            "name": "B",
                            "type": "Positive"
                        },
                        "dateDonated": 1653930000000,
                        "amount": 122,
                        "status": 1
                    }
                },
                {
                    "_id": "910424695097",
                    "name": "Tr\u1ea7n Th\u1ed1ng Nh\u1ea5t",
                    "dob": "439923600000",
                    "gender": "male",
                    "address": "Mỏ Cày Nam, Bến Tre",
                    "phone": "(+84) 563220150",
                    "email": "ttn11121983@gmail.com",
                    "transaction": {
                        "blood": {
                            "name": "AB",
                            "type": "Negative"
                        },
                        "dateDonated": 1649350800000,
                        "amount": 140,
                        "status": 1
                    }
                },
                {
                    "_id": "402688443981",
                    "name": "Ng\u00f4 B\u00ecnh Minh",
                    "dob": "990378000000",
                    "gender": "male",
                    "address": "Mộc Hóa, Long An",
                    "phone": "(+84) 094584753",
                    "email": "nbm21052001@gmail.com",
                    "transaction": {
                        "blood": {
                            "name": "AB",
                            "type": "Positive"
                        },
                        "dateDonated": 1649437200000,
                        "amount": 119,
                        "status": 1
                    }
                },
                {
                    "_id": "069460815499",
                    "name": "Ng\u00f4 L\u1ec7 Thu",
                    "dob": "665082000000",
                    "gender": "female",
                    "address": "Mỹ Tho, Tiền Giang",
                    "phone": "(+84) 853490960",
                    "email": "nlt29011991@gmail.com",
                    "transaction": {
                        "blood": {
                            "name": "O",
                            "type": "Negative"
                        },
                        "dateDonated": 1654621200000,
                        "amount": 111,
                        "status": -1,
                        "rejectReason": "Hepatitis B and C"
                    }
                },
                {
                    "_id": "619398913945",
                    "name": "L\u00ea Anh T\u00f9ng",
                    "dob": "562266000000",
                    "gender": "male",
                    "address": "Năm Căn, Cà Mau",
                    "phone": "(+84) 554305731",
                    "email": "lat27101987@gmail.com",
                    "transaction": {
                        "blood": {
                            "name": "A",
                            "type": "Negative"
                        },
                        "dateDonated": 1657645200000,
                        "amount": 132,
                        "status": -1,
                        "rejectReason": "Chronic alcoholism"
                    }
                },
                {
                    "_id": "027159132423",
                    "name": "B\u00f9i Ph\u01b0\u01a1ng Tr\u1ea1ch",
                    "dob": "809197200000",
                    "gender": "male",
                    "address": "Ngã Bảy, Hậu Giang",
                    "phone": "(+84) 223565077",
                    "email": "bpt24081995@gmail.com",
                    "transaction": {
                        "blood": {
                            "name": "A",
                            "type": "Positive"
                        },
                        "dateDonated": 1652547600000,
                        "amount": 117,
                        "status": -1,
                        "rejectReason": "Hepatitis B and C"
                    }
                }
            ]
        }
    ],
    "blood": [
        {
            "name": "A",
            "type": "Positive",
            "quantity": 70000
        },
        {
            "name": "A",
            "type": "Negative",
            "quantity": 60000
        },
        {
            "name": "B",
            "type": "Positive",
            "quantity": 75000
        },
        {
            "name": "B",
            "type": "Negative",
            "quantity": 80000
        },
        {
            "name": "AB",
            "type": "Positive",
            "quantity": 65000
        },
        {
            "name": "AB",
            "type": "Negative",
            "quantity": 50000
        },
        {
            "name": "O",
            "type": "Positive",
            "quantity": 60000
        },
        {
            "name": "O",
            "type": "Negative",
            "quantity": 70000
        },
        {
            "name": "Rh",
            "type": "Positive",
            "quantity": 4000
        },
        {
            "name": "Rh",
            "type": "Negative",
            "quantity": 3000
        }
    ],
    "eventSubmissions": [
        {
            "eventId": "1",
            "idCardNumber": "015170423564",
            "fullname": "Tr\u1ea7n Thanh Phong",
            "phone": "(+84) 754499576",
            "address": "Ngã 6, Hậu Giang",
            "email": "ttp30081989@gmail.com",
            "gender": "male",
            "dob": "620413200000",
            "latestDonationDate": "1618094074000",
            "dateSubmitted": "1641038400000"
        },
        {
            "eventId": "1",
            "idCardNumber": "331952647287",
            "fullname": "Ng\u00f4 C\u1ea3nh Tu\u1ea5n",
            "phone": "(+84) 032124499",
            "address": "Ô Môn, Cần Thơ",
            "email": "nct18121974@gmail.com",
            "gender": "male",
            "dob": "156528000000",
            "latestDonationDate": "1612996474000",
            "dateSubmitted": "1639569600000"
        },
        {
            "eventId": "1",
            "idCardNumber": "438174401806",
            "fullname": "Tr\u1ea7n B\u0103ng T\u00e2m",
            "phone": "(+84) 790066227",
            "address": "Cờ Đỏ, Cần Thơ",
            "email": "tbt09031995@gmail.com",
            "gender": "female",
            "dob": "794682000000",
            "latestDonationDate": "1581374074000",
            "dateSubmitted": "1639569600000"
        },
        {
            "eventId": "1",
            "idCardNumber": "054317564294",
            "fullname": "Ng\u00f4 Ph\u00fac Sinh",
            "phone": "(+84) 696197954",
            "address": "Thốt Nốt, Cần Thơ",
            "email": "nps20052001@gmail.com",
            "gender": "male",
            "dob": "990291600000",
            "latestDonationDate": "1602369274000",
            "dateSubmitted": "1639569600000"
        },
        {
            "eventId": "1",
            "idCardNumber": "848913663028",
            "fullname": "L\u00ea Thi\u1ec7u B\u1ea3o",
            "phone": "(+84) 624293629",
            "address": "Mộc Hóa, Long An",
            "email": "ltb15051971@gmail.com",
            "gender": "male",
            "dob": "43084800000",
            "latestDonationDate": "1605047674000",
            "dateSubmitted": "1639569600000"
        },
        {
            "eventId": "1",
            "idCardNumber": "380410686864",
            "fullname": "Tr\u1ea7n Kim Thy",
            "phone": "(+84) 596580266",
            "address": "Quận 1, TP HCM",
            "email": "tkt10021985@gmail.com",
            "gender": "female",
            "dob": "476816400000",
            "latestDonationDate": "1607601600000",
            "dateSubmitted": "1640001600000"
        },
        {
            "eventId": "2",
            "idCardNumber": "625164290733",
            "fullname": "Tr\u1ea7n Th\u00e0nh Sang",
            "phone": "(+84) 426121395",
            "address": "Quận 12, TP HCM",
            "email": "tts14111976@gmail.com",
            "gender": "male",
            "dob": "216752400000",
            "latestDonationDate": "1610193600000",
            "dateSubmitted": "1647277200000"
        },
        {
            "eventId": "2",
            "idCardNumber": "484714949896",
            "fullname": "Ng\u00f4 \u00d0\u00f4ng Tuy\u1ec1n",
            "phone": "(+84) 754499576",
            "address": "Cái Răng, Cần Thơ",
            "email": "ndt14071992@gmail.com",
            "gender": "female",
            "dob": "711046800000",
            "latestDonationDate": "1613649600000",
            "dateSubmitted": "1646049600000"
        },
        {
            "eventId": "2",
            "idCardNumber": "437249400607",
            "fullname": "L\u00ea Cam Th\u1ea3o",
            "phone": "(+84) 773828964",
            "address": "Phú Nhuận, TP HCM",
            "email": "lct04031993@gmail.com",
            "gender": "female",
            "dob": "731178000000",
            "latestDonationDate": "1620734400000",
            "dateSubmitted": "1646222400000"
        },
        {
            "eventId": "2",
            "idCardNumber": "537653285431",
            "fullname": "Nguy\u1ec5n Xu\u00e2n Nhi\u00ean",
            "phone": "(+84) 344475377",
            "address": "Cai Lậy, Tiền Giang",
            "email": "nxn30121971@gmail.com",
            "gender": "female",
            "dob": "62870400000",
            "latestDonationDate": "1594468800000",
            "dateSubmitted": "1646136000000"
        },
        {
            "eventId": "2",
            "idCardNumber": "532468928496",
            "fullname": "Nguy\u1ec5n Tr\u00e0 My",
            "phone": "(+84) 852510819",
            "address": "Cái Bè, Tiền Giang",
            "email": "ntm17052003@gmail.com",
            "gender": "female",
            "dob": "1053104400000",
            "latestDonationDate": "1598702400000",
            "dateSubmitted": "1646481600000"
        },
        {
            "eventId": "2",
            "idCardNumber": "343662199463",
            "fullname": "Nguy\u1ec5n H\u1ea1 Giang",
            "phone": "(+84) 178580451",
            "address": "Cần Đước, Long An",
            "email": "nhg08071970@gmail.com",
            "gender": "female",
            "dob": "16214400000",
            "latestDonationDate": "1598788800000",
            "dateSubmitted": "1646136000000"
        },
        {
            "eventId": "3",
            "idCardNumber": "343275880278",
            "fullname": "Tr\u1ea7n \u0110\u0103ng Quang",
            "phone": "(+84) 419413160",
            "address": "Châu Đốc, An Giang",
            "email": "tdq23071995@gmail.com",
            "gender": "male",
            "dob": "806432400000",
            "latestDonationDate": "1571832000000",
            "dateSubmitted": "1647345600000"
        },
        {
            "eventId": "3",
            "idCardNumber": "504321249636",
            "fullname": "Tr\u1ea7n H\u00f9ng T\u01b0\u1eddng",
            "phone": "(+84) 778268910",
            "address": "Chợ Gạo, Tiền Giang",
            "email": "tht06102002@gmail.com",
            "gender": "male",
            "dob": "1033837200000",
            "latestDonationDate": "1579780800000",
            "dateSubmitted": "1647518400000"
        },
        {
            "eventId": "3",
            "idCardNumber": "273488618725",
            "fullname": "Tr\u01b0\u01a1ng \u0110\u00f4ng Tuy\u1ec1n",
            "phone": "(+84) 397355135",
            "address": "Thốt Nốt, Cần Thơ",
            "email": "tdt12031985@gmail.com",
            "gender": "female",
            "dob": "479408400000",
            "latestDonationDate": "1577966400000",
            "dateSubmitted": "1647777600000"
        },
        {
            "eventId": "3",
            "idCardNumber": "105346519430",
            "fullname": "Ng\u00f4 Cao Nghi\u1ec7p",
            "phone": "(+84) 168470233",
            "address": "Dĩ An, Bình Dương",
            "email": "ncn25111988@gmail.com",
            "gender": "male",
            "dob": "596394000000",
            "latestDonationDate": "1578225600000",
            "dateSubmitted": "1647259200000"
        },
        {
            "eventId": "3",
            "idCardNumber": "788289929724",
            "fullname": "L\u00ea Y\u00ean \u00d0an",
            "phone": "(+84) 540727040",
            "address": "Giồng Riềng, Kiên Giang",
            "email": "lyd05071978@gmail.com",
            "gender": "female",
            "dob": "268419600000",
            "latestDonationDate": "1591358400000",
            "dateSubmitted": "1647432000000"
        },
        {
            "eventId": "3",
            "idCardNumber": "913542751853",
            "fullname": "B\u00f9i Vi\u1ec5n Ph\u01b0\u01a1ng",
            "phone": "(+84) 259678084",
            "address": "Gò Công, Tiền Giang",
            "email": "bvp29061987@gmail.com",
            "gender": "male",
            "dob": "551898000000",
            "latestDonationDate": "1591617600000",
            "dateSubmitted": "1647950400000"
        },
        {
            "eventId": "4",
            "idCardNumber": "569920221547",
            "fullname": "Ng\u00f4 T\u00e0i Nguy\u00ean",
            "phone": "(+84) 588485660",
            "address": "Hà Tiên, Kiên Giang",
            "email": "ntn10022000@gmail.com",
            "gender": "male",
            "dob": "950115600000",
            "latestDonationDate": "1596888000000",
            "dateSubmitted": "1648209600000"
        },
        {
            "eventId": "4",
            "idCardNumber": "171921185689",
            "fullname": "Nguy\u1ec5n Ch\u00ed C\u00f4ng",
            "phone": "(+84) 642371646",
            "address": "Kế Sách, Sóc Trăng",
            "email": "ncc19121994@gmail.com",
            "gender": "male",
            "dob": "787770000000",
            "latestDonationDate": "1617883200000",
            "dateSubmitted": "1648468800000"
        },
        {
            "eventId": "4",
            "idCardNumber": "070270856900",
            "fullname": "Nguy\u1ec5n \u00d0an Thu",
            "phone": "(+84) 582832042",
            "address": "Lai Vung, Đồng Tháp",
            "email": "ndt12062000@gmail.com",
            "gender": "female",
            "dob": "960742800000",
            "latestDonationDate": "1617451200000",
            "dateSubmitted": "1648555200000"
        },
        {
            "eventId": "4",
            "idCardNumber": "686346069843",
            "fullname": "Tr\u01b0\u01a1ng Ch\u00ed B\u1ea3o",
            "phone": "(+84) 507083295",
            "address": "Long Mỹ, Hậu Giang",
            "email": "tcb06122001@gmail.com",
            "gender": "male",
            "dob": "1007571600000",
            "latestDonationDate": "1620216000000",
            "dateSubmitted": "1648296000000"
        },
        {
            "eventId": "4",
            "idCardNumber": "910424695097",
            "fullname": "Tr\u1ea7n Th\u1ed1ng Nh\u1ea5t",
            "phone": "(+84) 563220150",
            "address": "Mỏ Cày Nam, Bến Tre",
            "email": "ttn11121983@gmail.com",
            "gender": "male",
            "dob": "439923600000",
            "latestDonationDate": "1612699200000",
            "dateSubmitted": "1648296000000"
        }
    ],
    "requests": [
        {
            "date": "1644235200000",
            "quantity": 7000,
            "blood": {
                "name": "AB",
                "type": "Negative"
            },
            "hospitalId": "0",
            "status": 1
        },
        {
            "date": "1649721600000",
            "quantity": 15000,
            "blood": {
                "name": "A",
                "type": "Positive"
            },
            "hospitalId": "0",
            "status": 1
        },
        {
            "date": "1644235200000",
            "quantity": 100000,
            "blood": {
                "name": "B",
                "type": "Negative"
            },
            "hospitalId": "0",
            "status": -1,
            "rejectReason": "Not enough blood"
        },
        {
            "date": "1644494400000",
            "quantity": 8000,
            "blood": {
                "name": "O",
                "type": "Positive"
            },
            "hospitalId": "0",
            "status": 1
        },
        {
            "date": "1646913600000",
            "quantity": 4000,
            "blood": {
                "name": "AB",
                "type": "Positive"
            },
            "hospitalId": "0",
            "status": 1
        },
        {
            "date": "1642593600000",
            "quantity": 90000,
            "blood": {
                "name": "A",
                "type": "Negative"
            },
            "hospitalId": "1",
            "status": -1,
            "rejectReason": "Not enough blood"
        },
        {
            "date": "1642680000000",
            "quantity": 7500,
            "blood": {
                "name": "B",
                "type": "Positive"
            },
            "hospitalId": "1",
            "status": 1
        },
        {
            "date": "1645704000000",
            "quantity": 9300,
            "blood": {
                "name": "O",
                "type": "Positive"
            },
            "hospitalId": "1",
            "status": 1
        },
        {
            "date": "1648857600000",
            "quantity": 9800,
            "blood": {
                "name": "O",
                "type": "Negative"
            },
            "hospitalId": "1",
            "status": 1
        },
        {
            "date": "1646049600000",
            "quantity": 200,
            "blood": {
                "name": "Rh",
                "type": "Negative"
            },
            "hospitalId": "1",
            "status": 1
        },
        {
            "date": "1641124800000",
            "quantity": 4000,
            "blood": {
                "name": "Rh",
                "type": "Positive"
            },
            "hospitalId": "2",
            "status": -1,
            "rejectReason": "Not enough blood"
        },
        {
            "date": "1641556800000",
            "quantity": 6000,
            "blood": {
                "name": "AB",
                "type": "Negative"
            },
            "hospitalId": "2",
            "status": 1
        },
        {
            "date": "1646654400000",
            "quantity": 7000,
            "blood": {
                "name": "O",
                "type": "Negative"
            },
            "hospitalId": "2",
            "status": 1
        },
        {
            "date": "1646654400000",
            "quantity": 10000,
            "blood": {
                "name": "A",
                "type": "Negative"
            },
            "hospitalId": "2",
            "status": 1
        },
        {
            "date": "1649203200000",
            "quantity": 12000,
            "blood": {
                "name": "B",
                "type": "Negative"
            },
            "hospitalId": "2",
            "status": 1
        },
        {
            "date": "1646654400000",
            "quantity": 13000,
            "blood": {
                "name": "O",
                "type": "Positive"
            },
            "hospitalId": "3",
            "status": 1
        },
        {
            "date": "1646568000000",
            "quantity": 8000,
            "blood": {
                "name": "B",
                "type": "Negative"
            },
            "hospitalId": "3",
            "status": 1
        },
        {
            "date": "1646568000000",
            "quantity": 6500,
            "blood": {
                "name": "AB",
                "type": "Positive"
            },
            "hospitalId": "3",
            "status": 1
        },
        {
            "date": "1646568000000",
            "quantity": 5500,
            "blood": {
                "name": "AB",
                "type": "Negative"
            },
            "hospitalId": "3",
            "status": 1
        }
    ]
}
